[
	{
		"id": 42405,
		"is_active": true,
		"name": "Eureka Valley Fire",
		"description": null,
		"lat": 41.5529899,
		"lng": -100.0203898,
		"address": "Near Eureka Valley Rd & 420 Rd, S/W of Anselmo",
		"geo_event_type": "wildfire",
		"data": {
			"geo_event_type": "wildfire",
			"is_prescribed": false,
			"prescribed_date_start": null,
			"prescribed_date_start_local": null,
			"is_fps": false,
			"containment": 85,
			"acreage": 4800,
			"links": [],
			"has_custom_evacuation_orders": false,
			"has_custom_evacuation_warnings": false,
			"has_custom_evacuation_advisories": false,
			"evacuation_orders": null,
			"evacuation_warnings": null,
			"evacuation_advisories": null,
			"evacuation_notes": null,
			"is_complex_parent": false,
			"reporter_only_notes": null,
			"temporarily_display_evac_zones": false
		},
		"date_created": "2025-02-24T21:55:02Z",
		"date_modified": "2025-03-02T20:50:23Z",
		"notification_type": "normal",
		"incident_id": null,
		"reporter_managed": true,
		"external_id": null,
		"external_source": null,
		"child_geo_events": [],
		"parent_geo_events": []
	},
	{
		"id": 42527,
		"is_active": true,
		"name": "East Table Fire",
		"description": null,
		"lat": 41.52132289211846,
		"lng": -99.7094585906585,
		"address": "Off E Table Rd & 806 Rd, N/E of Merna",
		"geo_event_type": "wildfire",
		"data": {
			"geo_event_type": "wildfire",
			"is_prescribed": false,
			"prescribed_date_start": null,
			"prescribed_date_start_local": null,
			"is_fps": false,
			"containment": 95,
			"acreage": 475,
			"links": [],
			"has_custom_evacuation_orders": false,
			"has_custom_evacuation_warnings": false,
			"has_custom_evacuation_advisories": false,
			"evacuation_orders": null,
			"evacuation_warnings": null,
			"evacuation_advisories": null,
			"evacuation_notes": null,
			"is_complex_parent": false,
			"reporter_only_notes": null,
			"temporarily_display_evac_zones": false
		},
		"date_created": "2025-02-26T02:33:13Z",
		"date_modified": "2025-03-02T03:02:33Z",
		"notification_type": "normal",
		"incident_id": null,
		"reporter_managed": true,
		"external_id": "8bdfae17-b9c3-43e2-ac0e-ed01872d93c9",
		"external_source": "wildcad",
		"child_geo_events": [],
		"parent_geo_events": []
	},
	{
		"id": 42599,
		"is_active": true,
		"name": "Lillian Fire",
		"description": null,
		"lat": 41.4743822,
		"lng": -99.6620145,
		"address": "Off Lillian Rd & Gates Rd, North of Broken Bow",
		"geo_event_type": "wildfire",
		"data": {
			"geo_event_type": "wildfire",
			"is_prescribed": false,
			"prescribed_date_start": null,
			"prescribed_date_start_local": null,
			"is_fps": false,
			"containment": 95,
			"acreage": 870,
			"links": [],
			"has_custom_evacuation_orders": false,
			"has_custom_evacuation_warnings": false,
			"has_custom_evacuation_advisories": false,
			"evacuation_orders": null,
			"evacuation_warnings": null,
			"evacuation_advisories": null,
			"evacuation_notes": null,
			"is_complex_parent": false,
			"reporter_only_notes": null,
			"temporarily_display_evac_zones": false
		},
		"date_created": "2025-02-27T01:41:12Z",
		"date_modified": "2025-03-01T20:38:00Z",
		"notification_type": "normal",
		"incident_id": null,
		"reporter_managed": true,
		"external_id": null,
		"external_source": null,
		"child_geo_events": [],
		"parent_geo_events": []
	},
	{
		"id": 42665,
		"is_active": true,
		"name": "Cross Timbers Fire",
		"description": null,
		"lat": 36.738889,
		"lng": -96.194167,
		"address": "4 miles W of Bartlesville, OK",
		"geo_event_type": "wildfire",
		"data": {
			"geo_event_type": "wildfire",
			"is_prescribed": false,
			"prescribed_date_start": null,
			"prescribed_date_start_local": null,
			"is_fps": null,
			"containment": 100,
			"acreage": 402.6,
			"links": null,
			"has_custom_evacuation_orders": false,
			"has_custom_evacuation_warnings": false,
			"has_custom_evacuation_advisories": false,
			"evacuation_orders": null,
			"evacuation_warnings": null,
			"evacuation_advisories": null,
			"evacuation_notes": null,
			"is_complex_parent": false,
			"reporter_only_notes": null,
			"temporarily_display_evac_zones": false
		},
		"date_created": "2025-02-27T22:40:11Z",
		"date_modified": "2025-03-03T16:10:19Z",
		"notification_type": "normal",
		"incident_id": null,
		"reporter_managed": false,
		"external_id": "{FF9B8643-14CD-48AC-BFEC-13EB5A1BFAD3}",
		"external_source": "nifc",
		"child_geo_events": [],
		"parent_geo_events": []
	},
	{
		"id": 42689,
		"is_active": true,
		"name": "Cedar Knob Fire",
		"description": null,
		"lat": 34.746667,
		"lng": -94.967778,
		"address": "45 miles SW of Ft. Smith, AR",
		"geo_event_type": "wildfire",
		"data": {
			"geo_event_type": "wildfire",
			"is_prescribed": false,
			"prescribed_date_start": null,
			"prescribed_date_start_local": null,
			"is_fps": null,
			"containment": 100,
			"acreage": 214,
			"links": null,
			"has_custom_evacuation_orders": false,
			"has_custom_evacuation_warnings": false,
			"has_custom_evacuation_advisories": false,
			"evacuation_orders": null,
			"evacuation_warnings": null,
			"evacuation_advisories": null,
			"evacuation_notes": null,
			"is_complex_parent": false,
			"reporter_only_notes": null,
			"temporarily_display_evac_zones": false
		},
		"date_created": "2025-02-28T04:30:10Z",
		"date_modified": "2025-03-03T15:40:19Z",
		"notification_type": "normal",
		"incident_id": null,
		"reporter_managed": false,
		"external_id": "{F479091D-5F81-4B97-801D-AECFB6321B4B}",
		"external_source": "nifc",
		"child_geo_events": [],
		"parent_geo_events": []
	},
	{
		"id": 42801,
		"is_active": true,
		"name": "Ludlow Fire",
		"description": null,
		"lat": 34.535278,
		"lng": -94.858611,
		"address": "1 mile W of Ludlow",
		"geo_event_type": "wildfire",
		"data": {
			"geo_event_type": "wildfire",
			"is_prescribed": false,
			"prescribed_date_start": null,
			"prescribed_date_start_local": null,
			"is_fps": false,
			"containment": 90,
			"acreage": 28,
			"links": null,
			"has_custom_evacuation_orders": false,
			"has_custom_evacuation_warnings": false,
			"has_custom_evacuation_advisories": false,
			"evacuation_orders": null,
			"evacuation_warnings": null,
			"evacuation_advisories": null,
			"evacuation_notes": null,
			"is_complex_parent": false,
			"reporter_only_notes": null,
			"temporarily_display_evac_zones": false
		},
		"date_created": "2025-03-01T03:46:04Z",
		"date_modified": "2025-03-02T17:58:17Z",
		"notification_type": "normal",
		"incident_id": null,
		"reporter_managed": true,
		"external_id": "{7A4D2855-E626-4123-B9F8-7F1EA1C07B12}",
		"external_source": "nifc",
		"child_geo_events": [],
		"parent_geo_events": []
	},
	{
		"id": 42802,
		"is_active": true,
		"name": "Sugar Road Fire",
		"description": null,
		"lat": 34.214444,
		"lng": -95.819722,
		"address": "3 miles SW of Darwin",
		"geo_event_type": "wildfire",
		"data": {
			"geo_event_type": "wildfire",
			"is_prescribed": false,
			"prescribed_date_start": null,
			"prescribed_date_start_local": null,
			"is_fps": false,
			"containment": 75,
			"acreage": 114,
			"links": null,
			"has_custom_evacuation_orders": false,
			"has_custom_evacuation_warnings": false,
			"has_custom_evacuation_advisories": false,
			"evacuation_orders": null,
			"evacuation_warnings": null,
			"evacuation_advisories": null,
			"evacuation_notes": null,
			"is_complex_parent": false,
			"reporter_only_notes": null,
			"temporarily_display_evac_zones": false
		},
		"date_created": "2025-03-01T04:06:04Z",
		"date_modified": "2025-03-02T17:57:23Z",
		"notification_type": "normal",
		"incident_id": null,
		"reporter_managed": true,
		"external_id": "{9A630E73-10BF-43DD-B5C3-FA2F2E4C34AA}",
		"external_source": "nifc",
		"child_geo_events": [],
		"parent_geo_events": []
	},
	{
		"id": 42805,
		"is_active": true,
		"name": "Mason Mountain Fire",
		"description": null,
		"lat": 34.47161982247272,
		"lng": -96.00004441342183,
		"address": "Approx 1.5 miles E of Stringtown off Hwy 43",
		"geo_event_type": "wildfire",
		"data": {
			"geo_event_type": "wildfire",
			"is_prescribed": false,
			"prescribed_date_start": null,
			"prescribed_date_start_local": null,
			"is_fps": false,
			"containment": 80,
			"acreage": 1871,
			"links": [],
			"has_custom_evacuation_orders": false,
			"has_custom_evacuation_warnings": false,
			"has_custom_evacuation_advisories": false,
			"evacuation_orders": null,
			"evacuation_warnings": null,
			"evacuation_advisories": null,
			"evacuation_notes": null,
			"is_complex_parent": false,
			"reporter_only_notes": null,
			"temporarily_display_evac_zones": false
		},
		"date_created": "2025-03-01T08:06:08Z",
		"date_modified": "2025-03-03T14:43:51Z",
		"notification_type": "normal",
		"incident_id": null,
		"reporter_managed": true,
		"external_id": "{79AD5B75-7E42-4274-BF5D-8B3255B4F0E2}",
		"external_source": "nifc",
		"child_geo_events": [],
		"parent_geo_events": []
	},
	{
		"id": 42811,
		"is_active": true,
		"name": "River Ranch Fire",
		"description": null,
		"lat": 35.145278,
		"lng": -96.0375,
		"address": "4.5 miles NE of Lamar, OK",
		"geo_event_type": "wildfire",
		"data": {
			"geo_event_type": "wildfire",
			"is_prescribed": false,
			"prescribed_date_start": null,
			"prescribed_date_start_local": null,
			"is_fps": null,
			"containment": 90,
			"acreage": 1100,
			"links": null,
			"has_custom_evacuation_orders": false,
			"has_custom_evacuation_warnings": false,
			"has_custom_evacuation_advisories": false,
			"evacuation_orders": null,
			"evacuation_warnings": null,
			"evacuation_advisories": null,
			"evacuation_notes": null,
			"is_complex_parent": false,
			"reporter_only_notes": null,
			"temporarily_display_evac_zones": false
		},
		"date_created": "2025-03-01T13:55:14Z",
		"date_modified": "2025-03-03T16:01:19Z",
		"notification_type": "normal",
		"incident_id": null,
		"reporter_managed": false,
		"external_id": "{A9CD310D-63FD-4BED-881D-43F5D332D0D1}",
		"external_source": "nifc",
		"child_geo_events": [],
		"parent_geo_events": []
	},
	{
		"id": 42816,
		"is_active": false,
		"name": "Rock Fire",
		"description": null,
		"lat": 34.640833,
		"lng": -96.591111,
		"address": null,
		"geo_event_type": "wildfire",
		"data": {
			"geo_event_type": "wildfire",
			"is_prescribed": false,
			"prescribed_date_start": null,
			"prescribed_date_start_local": null,
			"is_fps": null,
			"containment": null,
			"acreage": 9.6,
			"links": null,
			"has_custom_evacuation_orders": false,
			"has_custom_evacuation_warnings": false,
			"has_custom_evacuation_advisories": false,
			"evacuation_orders": null,
			"evacuation_warnings": null,
			"evacuation_advisories": null,
			"evacuation_notes": null,
			"is_complex_parent": false,
			"reporter_only_notes": null,
			"temporarily_display_evac_zones": false
		},
		"date_created": "2025-03-01T14:30:14Z",
		"date_modified": "2025-03-03T09:43:03Z",
		"notification_type": "normal",
		"incident_id": null,
		"reporter_managed": false,
		"external_id": "{4E1C363C-258C-444B-BF2D-AEA40171F8C4}",
		"external_source": "nifc",
		"child_geo_events": [],
		"parent_geo_events": []
	},
	{
		"id": 42835,
		"is_active": true,
		"name": "Green Acres Fire",
		"description": null,
		"lat": 43.39749367748951,
		"lng": -103.50911727576158,
		"address": "Southeast of Cascade Road (Highway 71) & Country View Road, South of Hot Springs",
		"geo_event_type": "wildfire",
		"data": {
			"geo_event_type": "wildfire",
			"is_prescribed": false,
			"prescribed_date_start": null,
			"prescribed_date_start_local": null,
			"is_fps": false,
			"containment": 75,
			"acreage": 340,
			"links": [],
			"has_custom_evacuation_orders": false,
			"has_custom_evacuation_warnings": false,
			"has_custom_evacuation_advisories": false,
			"evacuation_orders": null,
			"evacuation_warnings": null,
			"evacuation_advisories": null,
			"evacuation_notes": null,
			"is_complex_parent": false,
			"reporter_only_notes": null,
			"temporarily_display_evac_zones": false
		},
		"date_created": "2025-03-01T20:15:18Z",
		"date_modified": "2025-03-02T20:08:08Z",
		"notification_type": "normal",
		"incident_id": null,
		"reporter_managed": true,
		"external_id": "{9FEA5BBA-43DE-4926-9C9F-9D1D3FDB5C67}",
		"external_source": "nifc",
		"child_geo_events": [],
		"parent_geo_events": []
	},
	{
		"id": 42836,
		"is_active": false,
		"name": "Cass 0739 Fire",
		"description": null,
		"lat": 33.16643,
		"lng": -94.592521,
		"address": null,
		"geo_event_type": "wildfire",
		"data": {
			"geo_event_type": "wildfire",
			"is_prescribed": false,
			"prescribed_date_start": null,
			"prescribed_date_start_local": null,
			"is_fps": null,
			"containment": 100,
			"acreage": 3,
			"links": null,
			"has_custom_evacuation_orders": false,
			"has_custom_evacuation_warnings": false,
			"has_custom_evacuation_advisories": false,
			"evacuation_orders": null,
			"evacuation_warnings": null,
			"evacuation_advisories": null,
			"evacuation_notes": null,
			"is_complex_parent": false,
			"reporter_only_notes": null,
			"temporarily_display_evac_zones": false
		},
		"date_created": "2025-03-01T20:20:18Z",
		"date_modified": "2025-03-02T21:15:54Z",
		"notification_type": "normal",
		"incident_id": null,
		"reporter_managed": false,
		"external_id": "{C5FDF447-D334-47A1-8336-C0A8BF0EA64F}",
		"external_source": "nifc",
		"child_geo_events": [],
		"parent_geo_events": []
	},
	{
		"id": 42839,
		"is_active": false,
		"name": "Marie Fire",
		"description": null,
		"lat": 37.012667,
		"lng": -91.295917,
		"address": "2 Miles East of Winona, MO",
		"geo_event_type": "wildfire",
		"data": {
			"geo_event_type": "wildfire",
			"is_prescribed": false,
			"prescribed_date_start": null,
			"prescribed_date_start_local": null,
			"is_fps": null,
			"containment": 100,
			"acreage": 3.5,
			"links": null,
			"has_custom_evacuation_orders": false,
			"has_custom_evacuation_warnings": false,
			"has_custom_evacuation_advisories": false,
			"evacuation_orders": null,
			"evacuation_warnings": null,
			"evacuation_advisories": null,
			"evacuation_notes": null,
			"is_complex_parent": false,
			"reporter_only_notes": null,
			"temporarily_display_evac_zones": false
		},
		"date_created": "2025-03-01T20:47:39Z",
		"date_modified": "2025-03-03T17:50:42Z",
		"notification_type": "normal",
		"incident_id": null,
		"reporter_managed": false,
		"external_id": "6ffee39c-f1a2-4cc8-8f5d-1454097d651c",
		"external_source": "wildcad",
		"child_geo_events": [],
		"parent_geo_events": []
	},
	{
		"id": 42841,
		"is_active": true,
		"name": "Switchback Fire",
		"description": null,
		"lat": 34.573056,
		"lng": -95.589444,
		"address": "12 miles W of Clayton",
		"geo_event_type": "wildfire",
		"data": {
			"geo_event_type": "wildfire",
			"is_prescribed": false,
			"prescribed_date_start": null,
			"prescribed_date_start_local": null,
			"is_fps": null,
			"containment": 70,
			"acreage": 114,
			"links": null,
			"has_custom_evacuation_orders": false,
			"has_custom_evacuation_warnings": false,
			"has_custom_evacuation_advisories": false,
			"evacuation_orders": null,
			"evacuation_warnings": null,
			"evacuation_advisories": null,
			"evacuation_notes": null,
			"is_complex_parent": false,
			"reporter_only_notes": null,
			"temporarily_display_evac_zones": false
		},
		"date_created": "2025-03-01T21:05:19Z",
		"date_modified": "2025-03-02T22:05:55Z",
		"notification_type": "normal",
		"incident_id": null,
		"reporter_managed": false,
		"external_id": "{E789B36C-13EA-44B0-B363-9F27C22A2387}",
		"external_source": "nifc",
		"child_geo_events": [],
		"parent_geo_events": []
	},
	{
		"id": 42842,
		"is_active": false,
		"name": "Mason Creek Fire",
		"description": null,
		"lat": 31.485583,
		"lng": -93.837367,
		"address": null,
		"geo_event_type": "wildfire",
		"data": {
			"geo_event_type": "wildfire",
			"is_prescribed": false,
			"prescribed_date_start": null,
			"prescribed_date_start_local": null,
			"is_fps": null,
			"containment": null,
			"acreage": 0.5,
			"links": null,
			"has_custom_evacuation_orders": false,
			"has_custom_evacuation_warnings": false,
			"has_custom_evacuation_advisories": false,
			"evacuation_orders": null,
			"evacuation_warnings": null,
			"evacuation_advisories": null,
			"evacuation_notes": null,
			"is_complex_parent": false,
			"reporter_only_notes": null,
			"temporarily_display_evac_zones": false
		},
		"date_created": "2025-03-01T21:06:46Z",
		"date_modified": "2025-03-02T21:20:45Z",
		"notification_type": "normal",
		"incident_id": null,
		"reporter_managed": false,
		"external_id": "e3fcc3e7-8a60-43cd-91d8-31831e05fee3",
		"external_source": "wildcad",
		"child_geo_events": [],
		"parent_geo_events": []
	},
	{
		"id": 42848,
		"is_active": false,
		"name": "Dmi Fire",
		"description": null,
		"lat": 27.735704,
		"lng": -98.114007,
		"address": "500 Block of FM 2295, Alice, TX 78332",
		"geo_event_type": "wildfire",
		"data": {
			"geo_event_type": "wildfire",
			"is_prescribed": false,
			"prescribed_date_start": null,
			"prescribed_date_start_local": null,
			"is_fps": null,
			"containment": 100,
			"acreage": 6,
			"links": null,
			"has_custom_evacuation_orders": false,
			"has_custom_evacuation_warnings": false,
			"has_custom_evacuation_advisories": false,
			"evacuation_orders": null,
			"evacuation_warnings": null,
			"evacuation_advisories": null,
			"evacuation_notes": null,
			"is_complex_parent": false,
			"reporter_only_notes": null,
			"temporarily_display_evac_zones": false
		},
		"date_created": "2025-03-01T22:15:21Z",
		"date_modified": "2025-03-02T23:30:57Z",
		"notification_type": "normal",
		"incident_id": null,
		"reporter_managed": false,
		"external_id": "{27683BA9-16AA-4610-9A8C-7C2191F09E02}",
		"external_source": "nifc",
		"child_geo_events": [],
		"parent_geo_events": []
	},
	{
		"id": 42850,
		"is_active": false,
		"name": "Spring Water Well Fire",
		"description": null,
		"lat": 30.717572,
		"lng": -94.668956,
		"address": "200 Block of Water Well Rd, Livingston, TX 77351",
		"geo_event_type": "wildfire",
		"data": {
			"geo_event_type": "wildfire",
			"is_prescribed": false,
			"prescribed_date_start": null,
			"prescribed_date_start_local": null,
			"is_fps": null,
			"containment": null,
			"acreage": 1.8,
			"links": null,
			"has_custom_evacuation_orders": false,
			"has_custom_evacuation_warnings": false,
			"has_custom_evacuation_advisories": false,
			"evacuation_orders": null,
			"evacuation_warnings": null,
			"evacuation_advisories": null,
			"evacuation_notes": null,
			"is_complex_parent": false,
			"reporter_only_notes": null,
			"temporarily_display_evac_zones": false
		},
		"date_created": "2025-03-01T22:20:20Z",
		"date_modified": "2025-03-03T09:38:01Z",
		"notification_type": "normal",
		"incident_id": null,
		"reporter_managed": false,
		"external_id": "{EABAC6A1-77CF-44EE-96ED-FAB2C946A992}",
		"external_source": "nifc",
		"child_geo_events": [],
		"parent_geo_events": []
	},
	{
		"id": 42854,
		"is_active": true,
		"name": "Corbo Fire",
		"description": null,
		"lat": 36.44194942370919,
		"lng": -96.12460458473794,
		"address": "200 Block of Skylar Ln, Skiatook, OK 74070",
		"geo_event_type": "wildfire",
		"data": {
			"geo_event_type": "wildfire",
			"is_prescribed": false,
			"prescribed_date_start": null,
			"prescribed_date_start_local": null,
			"is_fps": false,
			"containment": null,
			"acreage": 12,
			"links": [],
			"has_custom_evacuation_orders": false,
			"has_custom_evacuation_warnings": false,
			"has_custom_evacuation_advisories": false,
			"evacuation_orders": null,
			"evacuation_warnings": null,
			"evacuation_advisories": null,
			"evacuation_notes": null,
			"is_complex_parent": false,
			"reporter_only_notes": null,
			"temporarily_display_evac_zones": false
		},
		"date_created": "2025-03-01T22:50:20Z",
		"date_modified": "2025-03-02T18:15:11Z",
		"notification_type": "normal",
		"incident_id": null,
		"reporter_managed": true,
		"external_id": "{01C9EAEE-B2B4-4C13-A10D-930C15B3EC6A}",
		"external_source": "nifc",
		"child_geo_events": [],
		"parent_geo_events": []
	},
	{
		"id": 42858,
		"is_active": true,
		"name": "Deep Fork Fire",
		"description": null,
		"lat": 35.5375,
		"lng": -96.010556,
		"address": "3 miles NE of Wilson, OK",
		"geo_event_type": "wildfire",
		"data": {
			"geo_event_type": "wildfire",
			"is_prescribed": false,
			"prescribed_date_start": null,
			"prescribed_date_start_local": null,
			"is_fps": null,
			"containment": 90,
			"acreage": 857,
			"links": null,
			"has_custom_evacuation_orders": false,
			"has_custom_evacuation_warnings": false,
			"has_custom_evacuation_advisories": false,
			"evacuation_orders": null,
			"evacuation_warnings": null,
			"evacuation_advisories": null,
			"evacuation_notes": null,
			"is_complex_parent": false,
			"reporter_only_notes": null,
			"temporarily_display_evac_zones": false
		},
		"date_created": "2025-03-01T23:15:21Z",
		"date_modified": "2025-03-03T16:05:19Z",
		"notification_type": "normal",
		"incident_id": null,
		"reporter_managed": false,
		"external_id": "{9FACCF35-07A4-4476-A2F1-97D5625FD618}",
		"external_source": "nifc",
		"child_geo_events": [],
		"parent_geo_events": []
	},
	{
		"id": 42860,
		"is_active": true,
		"name": "1950 Road Fire",
		"description": null,
		"lat": 34.182778,
		"lng": -95.495,
		"address": "4 miles SW of Rattan",
		"geo_event_type": "wildfire",
		"data": {
			"geo_event_type": "wildfire",
			"is_prescribed": false,
			"prescribed_date_start": null,
			"prescribed_date_start_local": null,
			"is_fps": false,
			"containment": 75,
			"acreage": 475,
			"links": null,
			"has_custom_evacuation_orders": false,
			"has_custom_evacuation_warnings": false,
			"has_custom_evacuation_advisories": false,
			"evacuation_orders": null,
			"evacuation_warnings": null,
			"evacuation_advisories": null,
			"evacuation_notes": null,
			"is_complex_parent": false,
			"reporter_only_notes": null,
			"temporarily_display_evac_zones": false
		},
		"date_created": "2025-03-01T23:55:21Z",
		"date_modified": "2025-03-03T17:24:38Z",
		"notification_type": "normal",
		"incident_id": null,
		"reporter_managed": true,
		"external_id": "{34154056-6D8C-4205-AE09-4702AE61CCA6}",
		"external_source": "nifc",
		"child_geo_events": [],
		"parent_geo_events": []
	},
	{
		"id": 42868,
		"is_active": true,
		"name": "Saddle Gap Fire",
		"description": null,
		"lat": 34.761333,
		"lng": -95.457667,
		"address": "8 miles SE of Hartshorne, OK",
		"geo_event_type": "wildfire",
		"data": {
			"geo_event_type": "wildfire",
			"is_prescribed": false,
			"prescribed_date_start": null,
			"prescribed_date_start_local": null,
			"is_fps": false,
			"containment": 40,
			"acreage": 12327,
			"links": null,
			"has_custom_evacuation_orders": false,
			"has_custom_evacuation_warnings": false,
			"has_custom_evacuation_advisories": false,
			"evacuation_orders": null,
			"evacuation_warnings": null,
			"evacuation_advisories": null,
			"evacuation_notes": null,
			"is_complex_parent": false,
			"reporter_only_notes": null,
			"temporarily_display_evac_zones": false
		},
		"date_created": "2025-03-02T05:05:42Z",
		"date_modified": "2025-03-03T15:05:34Z",
		"notification_type": "normal",
		"incident_id": null,
		"reporter_managed": true,
		"external_id": "{234E5C98-54D3-4D82-A986-84EA7D354EF3}",
		"external_source": "nifc",
		"child_geo_events": [],
		"parent_geo_events": []
	},
	{
		"id": 42869,
		"is_active": true,
		"name": "Clear Cut Fire",
		"description": null,
		"lat": 34.550556,
		"lng": -94.879444,
		"address": "3 miles NE of Ludlow",
		"geo_event_type": "wildfire",
		"data": {
			"geo_event_type": "wildfire",
			"is_prescribed": false,
			"prescribed_date_start": null,
			"prescribed_date_start_local": null,
			"is_fps": false,
			"containment": 70,
			"acreage": 128,
			"links": null,
			"has_custom_evacuation_orders": false,
			"has_custom_evacuation_warnings": false,
			"has_custom_evacuation_advisories": false,
			"evacuation_orders": null,
			"evacuation_warnings": null,
			"evacuation_advisories": null,
			"evacuation_notes": null,
			"is_complex_parent": false,
			"reporter_only_notes": null,
			"temporarily_display_evac_zones": false
		},
		"date_created": "2025-03-02T05:10:42Z",
		"date_modified": "2025-03-03T17:20:35Z",
		"notification_type": "normal",
		"incident_id": null,
		"reporter_managed": true,
		"external_id": "{570EAE25-D67F-41C2-B52E-2121BBCF1447}",
		"external_source": "nifc",
		"child_geo_events": [],
		"parent_geo_events": []
	},
	{
		"id": 42870,
		"is_active": true,
		"name": "Red Oak Peak Fire",
		"description": null,
		"lat": 34.965333,
		"lng": -95.0375,
		"address": "2.6 miles ENE of Red Oak, OK",
		"geo_event_type": "wildfire",
		"data": {
			"geo_event_type": "wildfire",
			"is_prescribed": false,
			"prescribed_date_start": null,
			"prescribed_date_start_local": null,
			"is_fps": false,
			"containment": 85,
			"acreage": 1080,
			"links": null,
			"has_custom_evacuation_orders": false,
			"has_custom_evacuation_warnings": false,
			"has_custom_evacuation_advisories": false,
			"evacuation_orders": null,
			"evacuation_warnings": null,
			"evacuation_advisories": null,
			"evacuation_notes": null,
			"is_complex_parent": false,
			"reporter_only_notes": null,
			"temporarily_display_evac_zones": false
		},
		"date_created": "2025-03-02T05:30:42Z",
		"date_modified": "2025-03-03T17:19:01Z",
		"notification_type": "normal",
		"incident_id": null,
		"reporter_managed": true,
		"external_id": "{C8CB97B6-E936-413D-98FD-6BA7A8014975}",
		"external_source": "nifc",
		"child_geo_events": [],
		"parent_geo_events": []
	},
	{
		"id": 42871,
		"is_active": true,
		"name": "Horse Heaven Road Fire",
		"description": null,
		"lat": 34.716167,
		"lng": -94.929167,
		"address": "2.9 miles NW of Whitesboro, OK",
		"geo_event_type": "wildfire",
		"data": {
			"geo_event_type": "wildfire",
			"is_prescribed": false,
			"prescribed_date_start": null,
			"prescribed_date_start_local": null,
			"is_fps": false,
			"containment": 90,
			"acreage": 105,
			"links": null,
			"has_custom_evacuation_orders": false,
			"has_custom_evacuation_warnings": false,
			"has_custom_evacuation_advisories": false,
			"evacuation_orders": null,
			"evacuation_warnings": null,
			"evacuation_advisories": null,
			"evacuation_notes": null,
			"is_complex_parent": false,
			"reporter_only_notes": null,
			"temporarily_display_evac_zones": false
		},
		"date_created": "2025-03-02T05:45:42Z",
		"date_modified": "2025-03-03T17:19:53Z",
		"notification_type": "normal",
		"incident_id": null,
		"reporter_managed": true,
		"external_id": "{CFF82261-9461-4782-A7D4-9257AB87D916}",
		"external_source": "nifc",
		"child_geo_events": [],
		"parent_geo_events": []
	},
	{
		"id": 42872,
		"is_active": true,
		"name": "Low Water Fire",
		"description": null,
		"lat": 34.6765,
		"lng": -95.782,
		"address": "5 miles SSW of Blanco, OK",
		"geo_event_type": "wildfire",
		"data": {
			"geo_event_type": "wildfire",
			"is_prescribed": false,
			"prescribed_date_start": null,
			"prescribed_date_start_local": null,
			"is_fps": false,
			"containment": 90,
			"acreage": 1215,
			"links": null,
			"has_custom_evacuation_orders": false,
			"has_custom_evacuation_warnings": false,
			"has_custom_evacuation_advisories": false,
			"evacuation_orders": null,
			"evacuation_warnings": null,
			"evacuation_advisories": null,
			"evacuation_notes": null,
			"is_complex_parent": false,
			"reporter_only_notes": null,
			"temporarily_display_evac_zones": false
		},
		"date_created": "2025-03-02T06:15:42Z",
		"date_modified": "2025-03-03T14:47:07Z",
		"notification_type": "normal",
		"incident_id": null,
		"reporter_managed": true,
		"external_id": "{CB8BC563-911E-4190-94ED-D2118CEED639}",
		"external_source": "nifc",
		"child_geo_events": [],
		"parent_geo_events": []
	},
	{
		"id": 42879,
		"is_active": false,
		"name": "Buzzard Fire",
		"description": null,
		"lat": 35.737222,
		"lng": -94.520167,
		"address": null,
		"geo_event_type": "wildfire",
		"data": {
			"geo_event_type": "wildfire",
			"is_prescribed": false,
			"prescribed_date_start": null,
			"prescribed_date_start_local": null,
			"is_fps": false,
			"containment": 100,
			"acreage": 100,
			"links": null,
			"has_custom_evacuation_orders": false,
			"has_custom_evacuation_warnings": false,
			"has_custom_evacuation_advisories": false,
			"evacuation_orders": null,
			"evacuation_warnings": null,
			"evacuation_advisories": null,
			"evacuation_notes": null,
			"is_complex_parent": false,
			"reporter_only_notes": null,
			"temporarily_display_evac_zones": false
		},
		"date_created": "2025-03-02T14:05:48Z",
		"date_modified": "2025-03-03T02:09:35Z",
		"notification_type": "normal",
		"incident_id": null,
		"reporter_managed": true,
		"external_id": "{7E71DD82-C91F-4335-8690-B64C880EBDDB}",
		"external_source": "nifc",
		"child_geo_events": [],
		"parent_geo_events": []
	},
	{
		"id": 42884,
		"is_active": false,
		"name": "Gordon Fire",
		"description": null,
		"lat": 34.2136,
		"lng": -97.5947,
		"address": null,
		"geo_event_type": "wildfire",
		"data": {
			"geo_event_type": "wildfire",
			"is_prescribed": false,
			"prescribed_date_start": null,
			"prescribed_date_start_local": null,
			"is_fps": null,
			"containment": null,
			"acreage": 3.8,
			"links": null,
			"has_custom_evacuation_orders": false,
			"has_custom_evacuation_warnings": false,
			"has_custom_evacuation_advisories": false,
			"evacuation_orders": null,
			"evacuation_warnings": null,
			"evacuation_advisories": null,
			"evacuation_notes": null,
			"is_complex_parent": false,
			"reporter_only_notes": null,
			"temporarily_display_evac_zones": false
		},
		"date_created": "2025-03-02T14:30:49Z",
		"date_modified": "2025-03-03T09:40:48Z",
		"notification_type": "normal",
		"incident_id": null,
		"reporter_managed": false,
		"external_id": "{D624CA07-F88F-4C88-8580-8C9519AD3895}",
		"external_source": "nifc",
		"child_geo_events": [],
		"parent_geo_events": []
	},
	{
		"id": 42888,
		"is_active": false,
		"name": "Cibecue Creek Fire",
		"description": null,
		"lat": 34.016167,
		"lng": -110.4934,
		"address": null,
		"geo_event_type": "wildfire",
		"data": {
			"geo_event_type": "wildfire",
			"is_prescribed": false,
			"prescribed_date_start": null,
			"prescribed_date_start_local": null,
			"is_fps": false,
			"containment": 100,
			"acreage": 1.5,
			"links": null,
			"has_custom_evacuation_orders": false,
			"has_custom_evacuation_warnings": false,
			"has_custom_evacuation_advisories": false,
			"evacuation_orders": null,
			"evacuation_warnings": null,
			"evacuation_advisories": null,
			"evacuation_notes": null,
			"is_complex_parent": false,
			"reporter_only_notes": null,
			"temporarily_display_evac_zones": false
		},
		"date_created": "2025-03-02T16:05:50Z",
		"date_modified": "2025-03-03T13:24:35Z",
		"notification_type": "normal",
		"incident_id": null,
		"reporter_managed": true,
		"external_id": "{86347EB8-7380-4CF6-BD23-E2B016811B82}",
		"external_source": "nifc",
		"child_geo_events": [],
		"parent_geo_events": []
	},
	{
		"id": 42890,
		"is_active": false,
		"name": "Jumper Fire",
		"description": null,
		"lat": 35.384444,
		"lng": -96.592222,
		"address": null,
		"geo_event_type": "wildfire",
		"data": {
			"geo_event_type": "wildfire",
			"is_prescribed": false,
			"prescribed_date_start": null,
			"prescribed_date_start_local": null,
			"is_fps": false,
			"containment": 100,
			"acreage": 8,
			"links": null,
			"has_custom_evacuation_orders": false,
			"has_custom_evacuation_warnings": false,
			"has_custom_evacuation_advisories": false,
			"evacuation_orders": null,
			"evacuation_warnings": null,
			"evacuation_advisories": null,
			"evacuation_notes": null,
			"is_complex_parent": false,
			"reporter_only_notes": null,
			"temporarily_display_evac_zones": false
		},
		"date_created": "2025-03-02T16:40:50Z",
		"date_modified": "2025-03-03T00:39:35Z",
		"notification_type": "normal",
		"incident_id": null,
		"reporter_managed": true,
		"external_id": "{03B2D5FE-7AB7-415E-A80D-C443CB3FA53C}",
		"external_source": "nifc",
		"child_geo_events": [],
		"parent_geo_events": []
	},
	{
		"id": 42892,
		"is_active": true,
		"name": "Dickey Junction Fire",
		"description": null,
		"lat": 35.83793,
		"lng": -92.953909,
		"address": null,
		"geo_event_type": "wildfire",
		"data": {
			"geo_event_type": "wildfire",
			"is_prescribed": false,
			"prescribed_date_start": null,
			"prescribed_date_start_local": null,
			"is_fps": null,
			"containment": null,
			"acreage": 97,
			"links": null,
			"has_custom_evacuation_orders": false,
			"has_custom_evacuation_warnings": false,
			"has_custom_evacuation_advisories": false,
			"evacuation_orders": null,
			"evacuation_warnings": null,
			"evacuation_advisories": null,
			"evacuation_notes": null,
			"is_complex_parent": false,
			"reporter_only_notes": null,
			"temporarily_display_evac_zones": false
		},
		"date_created": "2025-03-02T18:36:36Z",
		"date_modified": "2025-03-03T00:53:19Z",
		"notification_type": "normal",
		"incident_id": null,
		"reporter_managed": false,
		"external_id": "e40742c1-2919-4cc9-9e80-134baae57360",
		"external_source": "wildcad",
		"child_geo_events": [],
		"parent_geo_events": []
	},
	{
		"id": 42897,
		"is_active": false,
		"name": "Cass 0787 Fire",
		"description": null,
		"lat": 32.97565,
		"lng": -94.462583,
		"address": null,
		"geo_event_type": "wildfire",
		"data": {
			"geo_event_type": "wildfire",
			"is_prescribed": false,
			"prescribed_date_start": null,
			"prescribed_date_start_local": null,
			"is_fps": null,
			"containment": 100,
			"acreage": 1,
			"links": null,
			"has_custom_evacuation_orders": false,
			"has_custom_evacuation_warnings": false,
			"has_custom_evacuation_advisories": false,
			"evacuation_orders": null,
			"evacuation_warnings": null,
			"evacuation_advisories": null,
			"evacuation_notes": null,
			"is_complex_parent": false,
			"reporter_only_notes": null,
			"temporarily_display_evac_zones": false
		},
		"date_created": "2025-03-02T19:10:52Z",
		"date_modified": "2025-03-03T00:09:35Z",
		"notification_type": "normal",
		"incident_id": null,
		"reporter_managed": false,
		"external_id": "{8A0EBDE9-606C-4D30-BBF3-36CE386B9A1C}",
		"external_source": "nifc",
		"child_geo_events": [],
		"parent_geo_events": []
	},
	{
		"id": 42899,
		"is_active": false,
		"name": "OO Fire",
		"description": null,
		"lat": 39.09876990000001,
		"lng": -92.18715029999998,
		"address": "9500 block of  E Hwy OO, Hallsville",
		"geo_event_type": "wildfire",
		"data": {
			"geo_event_type": "wildfire",
			"is_prescribed": false,
			"prescribed_date_start": null,
			"prescribed_date_start_local": null,
			"is_fps": false,
			"containment": null,
			"acreage": null,
			"links": [],
			"has_custom_evacuation_orders": false,
			"has_custom_evacuation_warnings": false,
			"has_custom_evacuation_advisories": false,
			"evacuation_orders": null,
			"evacuation_warnings": null,
			"evacuation_advisories": null,
			"evacuation_notes": null,
			"is_complex_parent": false,
			"reporter_only_notes": null,
			"temporarily_display_evac_zones": false
		},
		"date_created": "2025-03-02T19:46:05Z",
		"date_modified": "2025-03-02T22:01:45Z",
		"notification_type": "normal",
		"incident_id": null,
		"reporter_managed": true,
		"external_id": null,
		"external_source": null,
		"child_geo_events": [],
		"parent_geo_events": []
	},
	{
		"id": 42902,
		"is_active": false,
		"name": "Upshur 0791 Fire",
		"description": null,
		"lat": 32.793844,
		"lng": -94.845386,
		"address": "4100 Block of Daffodil Rd, Gilmer, TX 75645",
		"geo_event_type": "wildfire",
		"data": {
			"geo_event_type": "wildfire",
			"is_prescribed": false,
			"prescribed_date_start": null,
			"prescribed_date_start_local": null,
			"is_fps": null,
			"containment": 100,
			"acreage": 18,
			"links": null,
			"has_custom_evacuation_orders": false,
			"has_custom_evacuation_warnings": false,
			"has_custom_evacuation_advisories": false,
			"evacuation_orders": null,
			"evacuation_warnings": null,
			"evacuation_advisories": null,
			"evacuation_notes": null,
			"is_complex_parent": false,
			"reporter_only_notes": null,
			"temporarily_display_evac_zones": false
		},
		"date_created": "2025-03-02T20:20:53Z",
		"date_modified": "2025-03-03T04:24:35Z",
		"notification_type": "normal",
		"incident_id": null,
		"reporter_managed": false,
		"external_id": "{09C09248-6E56-48F4-88D9-CF292178F389}",
		"external_source": "nifc",
		"child_geo_events": [],
		"parent_geo_events": []
	},
	{
		"id": 42903,
		"is_active": false,
		"name": "Tyler 0790 Fire",
		"description": null,
		"lat": 30.914444,
		"lng": -94.338611,
		"address": "3000 Block of Co Rd 3260, Texas 75938",
		"geo_event_type": "wildfire",
		"data": {
			"geo_event_type": "wildfire",
			"is_prescribed": false,
			"prescribed_date_start": null,
			"prescribed_date_start_local": null,
			"is_fps": null,
			"containment": 100,
			"acreage": 1.6,
			"links": null,
			"has_custom_evacuation_orders": false,
			"has_custom_evacuation_warnings": false,
			"has_custom_evacuation_advisories": false,
			"evacuation_orders": null,
			"evacuation_warnings": null,
			"evacuation_advisories": null,
			"evacuation_notes": null,
			"is_complex_parent": false,
			"reporter_only_notes": null,
			"temporarily_display_evac_zones": false
		},
		"date_created": "2025-03-02T20:25:53Z",
		"date_modified": "2025-03-03T01:09:35Z",
		"notification_type": "normal",
		"incident_id": null,
		"reporter_managed": false,
		"external_id": "{AFAF8DF9-89B0-473D-9C62-4D07D83F4701}",
		"external_source": "nifc",
		"child_geo_events": [],
		"parent_geo_events": []
	},
	{
		"id": 42904,
		"is_active": true,
		"name": "Vegetation Fire",
		"description": null,
		"lat": 29.87564912131009,
		"lng": -94.13316692675981,
		"address": "15000 Block of Country Club Road, Taylor Landing",
		"geo_event_type": "wildfire",
		"data": {
			"geo_event_type": "wildfire",
			"is_prescribed": false,
			"prescribed_date_start": null,
			"prescribed_date_start_local": null,
			"is_fps": false,
			"containment": null,
			"acreage": null,
			"links": [],
			"has_custom_evacuation_orders": false,
			"has_custom_evacuation_warnings": false,
			"has_custom_evacuation_advisories": false,
			"evacuation_orders": null,
			"evacuation_warnings": null,
			"evacuation_advisories": null,
			"evacuation_notes": null,
			"is_complex_parent": false,
			"reporter_only_notes": null,
			"temporarily_display_evac_zones": false
		},
		"date_created": "2025-03-02T20:27:53Z",
		"date_modified": "2025-03-02T23:09:17Z",
		"notification_type": "normal",
		"incident_id": null,
		"reporter_managed": true,
		"external_id": null,
		"external_source": null,
		"child_geo_events": [],
		"parent_geo_events": []
	},
	{
		"id": 42905,
		"is_active": false,
		"name": "QNV State - HWY 60 MM 215 Fire",
		"description": null,
		"lat": 33.26933,
		"lng": -111.2953,
		"address": null,
		"geo_event_type": "wildfire",
		"data": {
			"geo_event_type": "wildfire",
			"is_prescribed": false,
			"prescribed_date_start": null,
			"prescribed_date_start_local": null,
			"is_fps": false,
			"containment": 100,
			"acreage": 3,
			"links": null,
			"has_custom_evacuation_orders": false,
			"has_custom_evacuation_warnings": false,
			"has_custom_evacuation_advisories": false,
			"evacuation_orders": null,
			"evacuation_warnings": null,
			"evacuation_advisories": null,
			"evacuation_notes": null,
			"is_complex_parent": false,
			"reporter_only_notes": null,
			"temporarily_display_evac_zones": false
		},
		"date_created": "2025-03-02T20:31:31Z",
		"date_modified": "2025-03-03T03:24:35Z",
		"notification_type": "normal",
		"incident_id": null,
		"reporter_managed": true,
		"external_id": "9b5fff38-1533-45d5-bd37-7bff6fa205a6",
		"external_source": "wildcad",
		"child_geo_events": [],
		"parent_geo_events": []
	},
	{
		"id": 42906,
		"is_active": false,
		"name": "Walker 0788 Fire",
		"description": null,
		"lat": 30.772904,
		"lng": -95.782283,
		"address": null,
		"geo_event_type": "wildfire",
		"data": {
			"geo_event_type": "wildfire",
			"is_prescribed": false,
			"prescribed_date_start": null,
			"prescribed_date_start_local": null,
			"is_fps": null,
			"containment": 100,
			"acreage": 7,
			"links": null,
			"has_custom_evacuation_orders": false,
			"has_custom_evacuation_warnings": false,
			"has_custom_evacuation_advisories": false,
			"evacuation_orders": null,
			"evacuation_warnings": null,
			"evacuation_advisories": null,
			"evacuation_notes": null,
			"is_complex_parent": false,
			"reporter_only_notes": null,
			"temporarily_display_evac_zones": false
		},
		"date_created": "2025-03-02T20:35:53Z",
		"date_modified": "2025-03-03T03:09:35Z",
		"notification_type": "normal",
		"incident_id": null,
		"reporter_managed": false,
		"external_id": "{0F923816-1D9C-4CA8-9B63-BB8761DB08AD}",
		"external_source": "nifc",
		"child_geo_events": [],
		"parent_geo_events": []
	},
	{
		"id": 42907,
		"is_active": false,
		"name": "Jennings Fire",
		"description": null,
		"lat": 36.763142,
		"lng": -92.757213,
		"address": null,
		"geo_event_type": "wildfire",
		"data": {
			"geo_event_type": "wildfire",
			"is_prescribed": false,
			"prescribed_date_start": null,
			"prescribed_date_start_local": null,
			"is_fps": false,
			"containment": 100,
			"acreage": 5,
			"links": null,
			"has_custom_evacuation_orders": false,
			"has_custom_evacuation_warnings": false,
			"has_custom_evacuation_advisories": false,
			"evacuation_orders": null,
			"evacuation_warnings": null,
			"evacuation_advisories": null,
			"evacuation_notes": null,
			"is_complex_parent": false,
			"reporter_only_notes": null,
			"temporarily_display_evac_zones": false
		},
		"date_created": "2025-03-02T20:35:54Z",
		"date_modified": "2025-03-03T02:09:35Z",
		"notification_type": "normal",
		"incident_id": null,
		"reporter_managed": true,
		"external_id": "{D739997B-2187-44BD-A350-E531DDF42A34}",
		"external_source": "nifc",
		"child_geo_events": [],
		"parent_geo_events": []
	},
	{
		"id": 42910,
		"is_active": false,
		"name": "Snapper Fire",
		"description": null,
		"lat": 30.27202,
		"lng": -96.888253,
		"address": null,
		"geo_event_type": "wildfire",
		"data": {
			"geo_event_type": "wildfire",
			"is_prescribed": false,
			"prescribed_date_start": null,
			"prescribed_date_start_local": null,
			"is_fps": null,
			"containment": 100,
			"acreage": 7,
			"links": null,
			"has_custom_evacuation_orders": false,
			"has_custom_evacuation_warnings": false,
			"has_custom_evacuation_advisories": false,
			"evacuation_orders": null,
			"evacuation_warnings": null,
			"evacuation_advisories": null,
			"evacuation_notes": null,
			"is_complex_parent": false,
			"reporter_only_notes": null,
			"temporarily_display_evac_zones": false
		},
		"date_created": "2025-03-02T20:55:54Z",
		"date_modified": "2025-03-03T01:39:35Z",
		"notification_type": "normal",
		"incident_id": null,
		"reporter_managed": false,
		"external_id": "{907B4C73-95C3-4B51-AAFD-5A9EF2662DAB}",
		"external_source": "nifc",
		"child_geo_events": [],
		"parent_geo_events": []
	},
	{
		"id": 42911,
		"is_active": false,
		"name": "Harrison 0796 Fire",
		"description": null,
		"lat": 32.57081,
		"lng": -94.44011,
		"address": "1800 Block of Nesbitt Cutoff, Marshall, TX 75670",
		"geo_event_type": "wildfire",
		"data": {
			"geo_event_type": "wildfire",
			"is_prescribed": false,
			"prescribed_date_start": null,
			"prescribed_date_start_local": null,
			"is_fps": null,
			"containment": 100,
			"acreage": 3,
			"links": null,
			"has_custom_evacuation_orders": false,
			"has_custom_evacuation_warnings": false,
			"has_custom_evacuation_advisories": false,
			"evacuation_orders": null,
			"evacuation_warnings": null,
			"evacuation_advisories": null,
			"evacuation_notes": null,
			"is_complex_parent": false,
			"reporter_only_notes": null,
			"temporarily_display_evac_zones": false
		},
		"date_created": "2025-03-02T20:55:54Z",
		"date_modified": "2025-03-03T16:35:20Z",
		"notification_type": "normal",
		"incident_id": null,
		"reporter_managed": false,
		"external_id": "{BBD5B241-5466-4769-91C5-86BF7A718B73}",
		"external_source": "nifc",
		"child_geo_events": [],
		"parent_geo_events": []
	},
	{
		"id": 42912,
		"is_active": true,
		"name": "ARI - Cota Fire",
		"description": null,
		"lat": 31.566584,
		"lng": -111.280707,
		"address": null,
		"geo_event_type": "wildfire",
		"data": {
			"geo_event_type": "wildfire",
			"is_prescribed": false,
			"prescribed_date_start": null,
			"prescribed_date_start_local": null,
			"is_fps": null,
			"containment": null,
			"acreage": 30,
			"links": null,
			"has_custom_evacuation_orders": false,
			"has_custom_evacuation_warnings": false,
			"has_custom_evacuation_advisories": false,
			"evacuation_orders": null,
			"evacuation_warnings": null,
			"evacuation_advisories": null,
			"evacuation_notes": null,
			"is_complex_parent": false,
			"reporter_only_notes": null,
			"temporarily_display_evac_zones": false
		},
		"date_created": "2025-03-02T21:08:17Z",
		"date_modified": "2025-03-03T14:38:18Z",
		"notification_type": "normal",
		"incident_id": null,
		"reporter_managed": false,
		"external_id": "39537551-c5a6-4036-8680-d0cd2d3561ed",
		"external_source": "wildcad",
		"child_geo_events": [],
		"parent_geo_events": []
	},
	{
		"id": 42914,
		"is_active": false,
		"name": "Henderson 0789 Fire",
		"description": null,
		"lat": 32.141217,
		"lng": -95.716967,
		"address": "8700 Block of US-175, Larue, TX 75770",
		"geo_event_type": "wildfire",
		"data": {
			"geo_event_type": "wildfire",
			"is_prescribed": false,
			"prescribed_date_start": null,
			"prescribed_date_start_local": null,
			"is_fps": null,
			"containment": 100,
			"acreage": 1,
			"links": null,
			"has_custom_evacuation_orders": false,
			"has_custom_evacuation_warnings": false,
			"has_custom_evacuation_advisories": false,
			"evacuation_orders": null,
			"evacuation_warnings": null,
			"evacuation_advisories": null,
			"evacuation_notes": null,
			"is_complex_parent": false,
			"reporter_only_notes": null,
			"temporarily_display_evac_zones": false
		},
		"date_created": "2025-03-02T21:15:55Z",
		"date_modified": "2025-03-03T16:15:19Z",
		"notification_type": "normal",
		"incident_id": null,
		"reporter_managed": false,
		"external_id": "{DF0116AC-51F1-41AC-8FB8-B800878B26C4}",
		"external_source": "nifc",
		"child_geo_events": [],
		"parent_geo_events": []
	},
	{
		"id": 42916,
		"is_active": false,
		"name": "Lamar 0798 Fire",
		"description": null,
		"lat": 33.785014,
		"lng": -95.418517,
		"address": "1600 Block of County Rd 44480, Paris, TX 75462",
		"geo_event_type": "wildfire",
		"data": {
			"geo_event_type": "wildfire",
			"is_prescribed": false,
			"prescribed_date_start": null,
			"prescribed_date_start_local": null,
			"is_fps": null,
			"containment": 100,
			"acreage": 1,
			"links": null,
			"has_custom_evacuation_orders": false,
			"has_custom_evacuation_warnings": false,
			"has_custom_evacuation_advisories": false,
			"evacuation_orders": null,
			"evacuation_warnings": null,
			"evacuation_advisories": null,
			"evacuation_notes": null,
			"is_complex_parent": false,
			"reporter_only_notes": null,
			"temporarily_display_evac_zones": false
		},
		"date_created": "2025-03-02T21:35:55Z",
		"date_modified": "2025-03-02T22:15:56Z",
		"notification_type": "normal",
		"incident_id": null,
		"reporter_managed": false,
		"external_id": "{5737C252-FF0F-41C0-A726-964A0F9BADA3}",
		"external_source": "nifc",
		"child_geo_events": [],
		"parent_geo_events": []
	},
	{
		"id": 42917,
		"is_active": true,
		"name": "Round Fire",
		"description": null,
		"lat": 36.91475,
		"lng": -92.185,
		"address": null,
		"geo_event_type": "wildfire",
		"data": {
			"geo_event_type": "wildfire",
			"is_prescribed": false,
			"prescribed_date_start": null,
			"prescribed_date_start_local": null,
			"is_fps": false,
			"containment": 95,
			"acreage": 550,
			"links": null,
			"has_custom_evacuation_orders": false,
			"has_custom_evacuation_warnings": false,
			"has_custom_evacuation_advisories": false,
			"evacuation_orders": null,
			"evacuation_warnings": null,
			"evacuation_advisories": null,
			"evacuation_notes": null,
			"is_complex_parent": false,
			"reporter_only_notes": null,
			"temporarily_display_evac_zones": false
		},
		"date_created": "2025-03-02T21:42:33Z",
		"date_modified": "2025-03-03T14:19:16Z",
		"notification_type": "normal",
		"incident_id": null,
		"reporter_managed": true,
		"external_id": "3602a375-fb48-4787-a71e-953ca1578aa4",
		"external_source": "wildcad",
		"child_geo_events": [],
		"parent_geo_events": []
	},
	{
		"id": 42918,
		"is_active": false,
		"name": "Cass 0800 Fire",
		"description": null,
		"lat": 33.071332,
		"lng": -94.565205,
		"address": "200 Block of Co Rd 2929, Hughes Springs, TX 75656",
		"geo_event_type": "wildfire",
		"data": {
			"geo_event_type": "wildfire",
			"is_prescribed": false,
			"prescribed_date_start": null,
			"prescribed_date_start_local": null,
			"is_fps": null,
			"containment": 100,
			"acreage": 9,
			"links": null,
			"has_custom_evacuation_orders": false,
			"has_custom_evacuation_warnings": false,
			"has_custom_evacuation_advisories": false,
			"evacuation_orders": null,
			"evacuation_warnings": null,
			"evacuation_advisories": null,
			"evacuation_notes": null,
			"is_complex_parent": false,
			"reporter_only_notes": null,
			"temporarily_display_evac_zones": false
		},
		"date_created": "2025-03-02T21:50:55Z",
		"date_modified": "2025-03-03T03:39:35Z",
		"notification_type": "normal",
		"incident_id": null,
		"reporter_managed": false,
		"external_id": "{9CC803C9-D3C1-4DEB-A754-F60540884D32}",
		"external_source": "nifc",
		"child_geo_events": [],
		"parent_geo_events": []
	},
	{
		"id": 42919,
		"is_active": false,
		"name": "Silver Springs Fire",
		"description": null,
		"lat": 30.58769,
		"lng": -96.915919,
		"address": "Northwest of Silver Springs Road & Silver Springs Circle, Southeast of Rockdale",
		"geo_event_type": "wildfire",
		"data": {
			"geo_event_type": "wildfire",
			"is_prescribed": false,
			"prescribed_date_start": null,
			"prescribed_date_start_local": null,
			"is_fps": true,
			"containment": 0,
			"acreage": 50,
			"links": [],
			"has_custom_evacuation_orders": false,
			"has_custom_evacuation_warnings": false,
			"has_custom_evacuation_advisories": false,
			"evacuation_orders": null,
			"evacuation_warnings": null,
			"evacuation_advisories": null,
			"evacuation_notes": null,
			"is_complex_parent": false,
			"reporter_only_notes": null,
			"temporarily_display_evac_zones": false
		},
		"date_created": "2025-03-02T22:00:55Z",
		"date_modified": "2025-03-03T04:09:35Z",
		"notification_type": "normal",
		"incident_id": null,
		"reporter_managed": true,
		"external_id": "{88324949-EA11-4F6B-B5E0-0E4AC4BE9301}",
		"external_source": "nifc",
		"child_geo_events": [],
		"parent_geo_events": []
	},
	{
		"id": 42920,
		"is_active": false,
		"name": "Powerline Fire",
		"description": null,
		"lat": 37.686617,
		"lng": -91.124217,
		"address": "2 Miles South of Viburnum, MO",
		"geo_event_type": "wildfire",
		"data": {
			"geo_event_type": "wildfire",
			"is_prescribed": false,
			"prescribed_date_start": null,
			"prescribed_date_start_local": null,
			"is_fps": null,
			"containment": 100,
			"acreage": 2,
			"links": null,
			"has_custom_evacuation_orders": false,
			"has_custom_evacuation_warnings": false,
			"has_custom_evacuation_advisories": false,
			"evacuation_orders": null,
			"evacuation_warnings": null,
			"evacuation_advisories": null,
			"evacuation_notes": null,
			"is_complex_parent": false,
			"reporter_only_notes": null,
			"temporarily_display_evac_zones": false
		},
		"date_created": "2025-03-02T22:05:15Z",
		"date_modified": "2025-03-03T04:24:35Z",
		"notification_type": "normal",
		"incident_id": null,
		"reporter_managed": false,
		"external_id": "d3d606eb-da66-4691-9491-9373eb971ef6",
		"external_source": "wildcad",
		"child_geo_events": [],
		"parent_geo_events": []
	},
	{
		"id": 42923,
		"is_active": true,
		"name": "Quinton Fire",
		"description": null,
		"lat": 35.068889,
		"lng": -95.403889,
		"address": "6 miles NW of Robbers Cave State Park, Wilburton, OK",
		"geo_event_type": "wildfire",
		"data": {
			"geo_event_type": "wildfire",
			"is_prescribed": false,
			"prescribed_date_start": null,
			"prescribed_date_start_local": null,
			"is_fps": false,
			"containment": 40,
			"acreage": 294.7,
			"links": null,
			"has_custom_evacuation_orders": false,
			"has_custom_evacuation_warnings": false,
			"has_custom_evacuation_advisories": false,
			"evacuation_orders": null,
			"evacuation_warnings": null,
			"evacuation_advisories": null,
			"evacuation_notes": null,
			"is_complex_parent": false,
			"reporter_only_notes": null,
			"temporarily_display_evac_zones": false
		},
		"date_created": "2025-03-02T22:15:55Z",
		"date_modified": "2025-03-03T17:16:29Z",
		"notification_type": "normal",
		"incident_id": null,
		"reporter_managed": true,
		"external_id": "{37B3848C-1667-40FC-8DD4-23E596E728BD}",
		"external_source": "nifc",
		"child_geo_events": [],
		"parent_geo_events": []
	},
	{
		"id": 42925,
		"is_active": false,
		"name": "Franky Fire",
		"description": null,
		"lat": 35.445278,
		"lng": -96.458056,
		"address": "10800 Block of NS 368 Rd, Oklahoma 74884",
		"geo_event_type": "wildfire",
		"data": {
			"geo_event_type": "wildfire",
			"is_prescribed": false,
			"prescribed_date_start": null,
			"prescribed_date_start_local": null,
			"is_fps": false,
			"containment": 100,
			"acreage": 61,
			"links": null,
			"has_custom_evacuation_orders": false,
			"has_custom_evacuation_warnings": false,
			"has_custom_evacuation_advisories": false,
			"evacuation_orders": null,
			"evacuation_warnings": null,
			"evacuation_advisories": null,
			"evacuation_notes": null,
			"is_complex_parent": false,
			"reporter_only_notes": null,
			"temporarily_display_evac_zones": false
		},
		"date_created": "2025-03-02T22:30:56Z",
		"date_modified": "2025-03-03T06:39:35Z",
		"notification_type": "normal",
		"incident_id": null,
		"reporter_managed": true,
		"external_id": "{3DB4DBCD-3F27-4FC4-BD6A-794D729B087B}",
		"external_source": "nifc",
		"child_geo_events": [],
		"parent_geo_events": []
	},
	{
		"id": 42926,
		"is_active": false,
		"name": "Rebar Fire",
		"description": null,
		"lat": 31.07958,
		"lng": -96.23485,
		"address": "12500 Block of Co Rd 4691, Hilltop Lakes, TX 77871",
		"geo_event_type": "wildfire",
		"data": {
			"geo_event_type": "wildfire",
			"is_prescribed": false,
			"prescribed_date_start": null,
			"prescribed_date_start_local": null,
			"is_fps": null,
			"containment": 100,
			"acreage": 1.5,
			"links": null,
			"has_custom_evacuation_orders": false,
			"has_custom_evacuation_warnings": false,
			"has_custom_evacuation_advisories": false,
			"evacuation_orders": null,
			"evacuation_warnings": null,
			"evacuation_advisories": null,
			"evacuation_notes": null,
			"is_complex_parent": false,
			"reporter_only_notes": null,
			"temporarily_display_evac_zones": false
		},
		"date_created": "2025-03-02T22:30:56Z",
		"date_modified": "2025-03-03T04:24:35Z",
		"notification_type": "normal",
		"incident_id": null,
		"reporter_managed": false,
		"external_id": "{C0F232FC-AC31-4675-A960-2E9751FD2716}",
		"external_source": "nifc",
		"child_geo_events": [],
		"parent_geo_events": []
	},
	{
		"id": 42927,
		"is_active": false,
		"name": "Burkhart Fire",
		"description": null,
		"lat": 37.437212,
		"lng": -92.20631,
		"address": null,
		"geo_event_type": "wildfire",
		"data": {
			"geo_event_type": "wildfire",
			"is_prescribed": false,
			"prescribed_date_start": null,
			"prescribed_date_start_local": null,
			"is_fps": null,
			"containment": 100,
			"acreage": 50,
			"links": null,
			"has_custom_evacuation_orders": false,
			"has_custom_evacuation_warnings": false,
			"has_custom_evacuation_advisories": false,
			"evacuation_orders": null,
			"evacuation_warnings": null,
			"evacuation_advisories": null,
			"evacuation_notes": null,
			"is_complex_parent": false,
			"reporter_only_notes": null,
			"temporarily_display_evac_zones": false
		},
		"date_created": "2025-03-02T22:47:24Z",
		"date_modified": "2025-03-03T08:54:35Z",
		"notification_type": "normal",
		"incident_id": null,
		"reporter_managed": false,
		"external_id": "989be4ea-798c-4219-9470-ea256f5e2d88",
		"external_source": "wildcad",
		"child_geo_events": [],
		"parent_geo_events": []
	},
	{
		"id": 42928,
		"is_active": false,
		"name": "Vegetation Fire",
		"description": null,
		"lat": 39.1133053,
		"lng": -92.2892163,
		"address": "13700 Block of North Robinson Road, West of Hallsville",
		"geo_event_type": "wildfire",
		"data": {
			"geo_event_type": "wildfire",
			"is_prescribed": false,
			"prescribed_date_start": null,
			"prescribed_date_start_local": null,
			"is_fps": false,
			"containment": null,
			"acreage": null,
			"links": [],
			"has_custom_evacuation_orders": false,
			"has_custom_evacuation_warnings": false,
			"has_custom_evacuation_advisories": false,
			"evacuation_orders": null,
			"evacuation_warnings": null,
			"evacuation_advisories": null,
			"evacuation_notes": null,
			"is_complex_parent": false,
			"reporter_only_notes": null,
			"temporarily_display_evac_zones": false
		},
		"date_created": "2025-03-02T22:52:28Z",
		"date_modified": "2025-03-03T06:48:13Z",
		"notification_type": "normal",
		"incident_id": null,
		"reporter_managed": true,
		"external_id": null,
		"external_source": null,
		"child_geo_events": [],
		"parent_geo_events": []
	},
	{
		"id": 42932,
		"is_active": false,
		"name": "Abraham Fire",
		"description": null,
		"lat": 39.38762,
		"lng": -112.70854,
		"address": "2300 Block of 7000 W, Hinckley, UT 84635",
		"geo_event_type": "wildfire",
		"data": {
			"geo_event_type": "wildfire",
			"is_prescribed": false,
			"prescribed_date_start": null,
			"prescribed_date_start_local": null,
			"is_fps": null,
			"containment": 100,
			"acreage": 5,
			"links": null,
			"has_custom_evacuation_orders": false,
			"has_custom_evacuation_warnings": false,
			"has_custom_evacuation_advisories": false,
			"evacuation_orders": null,
			"evacuation_warnings": null,
			"evacuation_advisories": null,
			"evacuation_notes": null,
			"is_complex_parent": false,
			"reporter_only_notes": null,
			"temporarily_display_evac_zones": false
		},
		"date_created": "2025-03-02T23:42:25Z",
		"date_modified": "2025-03-03T14:32:02Z",
		"notification_type": "normal",
		"incident_id": null,
		"reporter_managed": false,
		"external_id": "4b2e3ee0-e04a-4988-8bd0-c09ab4386fff",
		"external_source": "wildcad",
		"child_geo_events": [],
		"parent_geo_events": []
	},
	{
		"id": 42933,
		"is_active": true,
		"name": "Atkinson Fire",
		"description": null,
		"lat": 31.113982,
		"lng": -97.705506,
		"address": "2800 Block of Atkinson Ave, Killeen, TX 76543",
		"geo_event_type": "wildfire",
		"data": {
			"geo_event_type": "wildfire",
			"is_prescribed": false,
			"prescribed_date_start": null,
			"prescribed_date_start_local": null,
			"is_fps": null,
			"containment": 90,
			"acreage": 16,
			"links": null,
			"has_custom_evacuation_orders": false,
			"has_custom_evacuation_warnings": false,
			"has_custom_evacuation_advisories": false,
			"evacuation_orders": null,
			"evacuation_warnings": null,
			"evacuation_advisories": null,
			"evacuation_notes": null,
			"is_complex_parent": false,
			"reporter_only_notes": null,
			"temporarily_display_evac_zones": false
		},
		"date_created": "2025-03-02T23:45:57Z",
		"date_modified": "2025-03-03T03:00:59Z",
		"notification_type": "normal",
		"incident_id": null,
		"reporter_managed": false,
		"external_id": "{428F8441-CDC4-4C1B-AA5F-42276E5FA90C}",
		"external_source": "nifc",
		"child_geo_events": [],
		"parent_geo_events": []
	},
	{
		"id": 42934,
		"is_active": false,
		"name": "Harp Road Fire",
		"description": null,
		"lat": 44.308333,
		"lng": -103.378367,
		"address": "21300 Block of Harp Rd, Sturgis, SD 57785",
		"geo_event_type": "wildfire",
		"data": {
			"geo_event_type": "wildfire",
			"is_prescribed": false,
			"prescribed_date_start": null,
			"prescribed_date_start_local": null,
			"is_fps": false,
			"containment": 100,
			"acreage": 1.4,
			"links": null,
			"has_custom_evacuation_orders": false,
			"has_custom_evacuation_warnings": false,
			"has_custom_evacuation_advisories": false,
			"evacuation_orders": null,
			"evacuation_warnings": null,
			"evacuation_advisories": null,
			"evacuation_notes": null,
			"is_complex_parent": false,
			"reporter_only_notes": null,
			"temporarily_display_evac_zones": false
		},
		"date_created": "2025-03-02T23:45:57Z",
		"date_modified": "2025-03-03T13:24:35Z",
		"notification_type": "normal",
		"incident_id": null,
		"reporter_managed": true,
		"external_id": "{EDFBA7B9-7A6F-4350-A871-6DCB915A6FA4}",
		"external_source": "nifc",
		"child_geo_events": [],
		"parent_geo_events": []
	},
	{
		"id": 42936,
		"is_active": false,
		"name": "Cherokee 0805 Fire",
		"description": null,
		"lat": 31.992274,
		"lng": -95.25526,
		"address": "1200 Block of 4101, Jacksonville, TX 75766",
		"geo_event_type": "wildfire",
		"data": {
			"geo_event_type": "wildfire",
			"is_prescribed": false,
			"prescribed_date_start": null,
			"prescribed_date_start_local": null,
			"is_fps": null,
			"containment": 100,
			"acreage": 21,
			"links": null,
			"has_custom_evacuation_orders": false,
			"has_custom_evacuation_warnings": false,
			"has_custom_evacuation_advisories": false,
			"evacuation_orders": null,
			"evacuation_warnings": null,
			"evacuation_advisories": null,
			"evacuation_notes": null,
			"is_complex_parent": false,
			"reporter_only_notes": null,
			"temporarily_display_evac_zones": false
		},
		"date_created": "2025-03-03T00:05:57Z",
		"date_modified": "2025-03-03T07:09:35Z",
		"notification_type": "normal",
		"incident_id": null,
		"reporter_managed": false,
		"external_id": "{530E9283-1EA1-431F-8C62-E817B5A49237}",
		"external_source": "nifc",
		"child_geo_events": [],
		"parent_geo_events": []
	},
	{
		"id": 42940,
		"is_active": false,
		"name": "Smith 0806 Fire",
		"description": null,
		"lat": 32.454667,
		"lng": -95.2965,
		"address": "900 Block of County Rd 310 W, Tyler, TX 75706",
		"geo_event_type": "wildfire",
		"data": {
			"geo_event_type": "wildfire",
			"is_prescribed": false,
			"prescribed_date_start": null,
			"prescribed_date_start_local": null,
			"is_fps": null,
			"containment": 100,
			"acreage": 38,
			"links": null,
			"has_custom_evacuation_orders": false,
			"has_custom_evacuation_warnings": false,
			"has_custom_evacuation_advisories": false,
			"evacuation_orders": null,
			"evacuation_warnings": null,
			"evacuation_advisories": null,
			"evacuation_notes": null,
			"is_complex_parent": false,
			"reporter_only_notes": null,
			"temporarily_display_evac_zones": false
		},
		"date_created": "2025-03-03T00:40:58Z",
		"date_modified": "2025-03-03T10:54:35Z",
		"notification_type": "normal",
		"incident_id": null,
		"reporter_managed": false,
		"external_id": "{FDAD7C09-1C33-49B8-983E-B5862DFD5C1C}",
		"external_source": "nifc",
		"child_geo_events": [],
		"parent_geo_events": []
	},
	{
		"id": 42943,
		"is_active": true,
		"name": "Prairie Creek Fire",
		"description": null,
		"lat": 37.685617,
		"lng": -92.403967,
		"address": null,
		"geo_event_type": "wildfire",
		"data": {
			"geo_event_type": "wildfire",
			"is_prescribed": false,
			"prescribed_date_start": null,
			"prescribed_date_start_local": null,
			"is_fps": null,
			"containment": 100,
			"acreage": 75,
			"links": null,
			"has_custom_evacuation_orders": false,
			"has_custom_evacuation_warnings": false,
			"has_custom_evacuation_advisories": false,
			"evacuation_orders": null,
			"evacuation_warnings": null,
			"evacuation_advisories": null,
			"evacuation_notes": null,
			"is_complex_parent": false,
			"reporter_only_notes": null,
			"temporarily_display_evac_zones": false
		},
		"date_created": "2025-03-03T01:49:25Z",
		"date_modified": "2025-03-03T13:56:43Z",
		"notification_type": "normal",
		"incident_id": null,
		"reporter_managed": false,
		"external_id": "3302d145-a544-40d2-aab6-ae3b19b5877b",
		"external_source": "wildcad",
		"child_geo_events": [],
		"parent_geo_events": []
	},
	{
		"id": 42944,
		"is_active": true,
		"name": "Ghost Point Fire",
		"description": null,
		"lat": 34.705833,
		"lng": -95.721667,
		"address": "5 miles SE of Blanco, OK",
		"geo_event_type": "wildfire",
		"data": {
			"geo_event_type": "wildfire",
			"is_prescribed": false,
			"prescribed_date_start": null,
			"prescribed_date_start_local": null,
			"is_fps": false,
			"containment": 40,
			"acreage": 315,
			"links": null,
			"has_custom_evacuation_orders": false,
			"has_custom_evacuation_warnings": false,
			"has_custom_evacuation_advisories": false,
			"evacuation_orders": null,
			"evacuation_warnings": null,
			"evacuation_advisories": null,
			"evacuation_notes": null,
			"is_complex_parent": false,
			"reporter_only_notes": null,
			"temporarily_display_evac_zones": false
		},
		"date_created": "2025-03-03T02:15:59Z",
		"date_modified": "2025-03-03T17:23:10Z",
		"notification_type": "normal",
		"incident_id": null,
		"reporter_managed": true,
		"external_id": "{9E6A95DB-4F66-42D9-80F0-466707B1DF67}",
		"external_source": "nifc",
		"child_geo_events": [],
		"parent_geo_events": []
	},
	{
		"id": 42945,
		"is_active": false,
		"name": "Cemetery Fire",
		"description": null,
		"lat": 32.711051175234374,
		"lng": -117.11049051208741,
		"address": "3900 Block of Market Street, Mount Hope Cemetery - San Diego",
		"geo_event_type": "wildfire",
		"data": {
			"geo_event_type": "wildfire",
			"is_prescribed": false,
			"prescribed_date_start": null,
			"prescribed_date_start_local": null,
			"is_fps": true,
			"containment": null,
			"acreage": 0.5,
			"links": [],
			"has_custom_evacuation_orders": false,
			"has_custom_evacuation_warnings": false,
			"has_custom_evacuation_advisories": false,
			"evacuation_orders": null,
			"evacuation_warnings": null,
			"evacuation_advisories": null,
			"evacuation_notes": null,
			"is_complex_parent": false,
			"reporter_only_notes": null,
			"temporarily_display_evac_zones": false
		},
		"date_created": "2025-03-03T03:08:28Z",
		"date_modified": "2025-03-03T10:09:35Z",
		"notification_type": "normal",
		"incident_id": null,
		"reporter_managed": true,
		"external_id": null,
		"external_source": null,
		"child_geo_events": [],
		"parent_geo_events": []
	},
	{
		"id": 42948,
		"is_active": true,
		"name": "Dunbar Fire",
		"description": null,
		"lat": 34.141944,
		"lng": -95.530833,
		"address": "1 mile NE of Dunbar",
		"geo_event_type": "wildfire",
		"data": {
			"geo_event_type": "wildfire",
			"is_prescribed": false,
			"prescribed_date_start": null,
			"prescribed_date_start_local": null,
			"is_fps": null,
			"containment": 50,
			"acreage": 151,
			"links": null,
			"has_custom_evacuation_orders": false,
			"has_custom_evacuation_warnings": false,
			"has_custom_evacuation_advisories": false,
			"evacuation_orders": null,
			"evacuation_warnings": null,
			"evacuation_advisories": null,
			"evacuation_notes": null,
			"is_complex_parent": false,
			"reporter_only_notes": null,
			"temporarily_display_evac_zones": false
		},
		"date_created": "2025-03-03T06:51:11Z",
		"date_modified": "2025-03-03T06:51:11Z",
		"notification_type": "normal",
		"incident_id": null,
		"reporter_managed": false,
		"external_id": "{680715AB-1AE8-482C-B65A-668EFFDE04C5}",
		"external_source": "nifc",
		"child_geo_events": [],
		"parent_geo_events": []
	},
	{
		"id": 42949,
		"is_active": true,
		"name": "Cowhead Fire",
		"description": null,
		"lat": 35.571944,
		"lng": -94.877222,
		"address": "3 miles E of Marble City",
		"geo_event_type": "wildfire",
		"data": {
			"geo_event_type": "wildfire",
			"is_prescribed": false,
			"prescribed_date_start": null,
			"prescribed_date_start_local": null,
			"is_fps": null,
			"containment": 40,
			"acreage": 192,
			"links": null,
			"has_custom_evacuation_orders": false,
			"has_custom_evacuation_warnings": false,
			"has_custom_evacuation_advisories": false,
			"evacuation_orders": null,
			"evacuation_warnings": null,
			"evacuation_advisories": null,
			"evacuation_notes": null,
			"is_complex_parent": false,
			"reporter_only_notes": null,
			"temporarily_display_evac_zones": false
		},
		"date_created": "2025-03-03T07:15:12Z",
		"date_modified": "2025-03-03T07:15:12Z",
		"notification_type": "normal",
		"incident_id": null,
		"reporter_managed": false,
		"external_id": "{57A84091-C329-4098-BB28-59E718327F14}",
		"external_source": "nifc",
		"child_geo_events": [],
		"parent_geo_events": []
	},
	{
		"id": 42950,
		"is_active": true,
		"name": "Fletcher Mountain Fire",
		"description": null,
		"lat": 35.734722,
		"lng": -94.685556,
		"address": "4 miles SW of Blanch",
		"geo_event_type": "wildfire",
		"data": {
			"geo_event_type": "wildfire",
			"is_prescribed": false,
			"prescribed_date_start": null,
			"prescribed_date_start_local": null,
			"is_fps": null,
			"containment": 40,
			"acreage": 184,
			"links": null,
			"has_custom_evacuation_orders": false,
			"has_custom_evacuation_warnings": false,
			"has_custom_evacuation_advisories": false,
			"evacuation_orders": null,
			"evacuation_warnings": null,
			"evacuation_advisories": null,
			"evacuation_notes": null,
			"is_complex_parent": false,
			"reporter_only_notes": null,
			"temporarily_display_evac_zones": false
		},
		"date_created": "2025-03-03T07:20:12Z",
		"date_modified": "2025-03-03T07:20:12Z",
		"notification_type": "normal",
		"incident_id": null,
		"reporter_managed": false,
		"external_id": "{4889CDE6-3B1C-48E6-B2FA-C78ED10C1888}",
		"external_source": "nifc",
		"child_geo_events": [],
		"parent_geo_events": []
	},
	{
		"id": 42953,
		"is_active": true,
		"name": "Big Springs State Assist Fire",
		"description": null,
		"lat": 35.950283,
		"lng": -92.275133,
		"address": null,
		"geo_event_type": "wildfire",
		"data": {
			"geo_event_type": "wildfire",
			"is_prescribed": false,
			"prescribed_date_start": null,
			"prescribed_date_start_local": null,
			"is_fps": null,
			"containment": null,
			"acreage": 9,
			"links": null,
			"has_custom_evacuation_orders": false,
			"has_custom_evacuation_warnings": false,
			"has_custom_evacuation_advisories": false,
			"evacuation_orders": null,
			"evacuation_warnings": null,
			"evacuation_advisories": null,
			"evacuation_notes": null,
			"is_complex_parent": false,
			"reporter_only_notes": null,
			"temporarily_display_evac_zones": false
		},
		"date_created": "2025-03-03T13:11:39Z",
		"date_modified": "2025-03-03T14:53:38Z",
		"notification_type": "normal",
		"incident_id": null,
		"reporter_managed": false,
		"external_id": "5b7b6b34-92cc-45bb-8393-53265b7226ee",
		"external_source": "wildcad",
		"child_geo_events": [],
		"parent_geo_events": []
	},
	{
		"id": 42957,
		"is_active": true,
		"name": "S. Gaines Creek Fire",
		"description": null,
		"lat": 34.813889,
		"lng": -95.335,
		"address": "4 miles SW of Damon, OK",
		"geo_event_type": "wildfire",
		"data": {
			"geo_event_type": "wildfire",
			"is_prescribed": false,
			"prescribed_date_start": null,
			"prescribed_date_start_local": null,
			"is_fps": false,
			"containment": 40,
			"acreage": 215,
			"links": null,
			"has_custom_evacuation_orders": false,
			"has_custom_evacuation_warnings": false,
			"has_custom_evacuation_advisories": false,
			"evacuation_orders": null,
			"evacuation_warnings": null,
			"evacuation_advisories": null,
			"evacuation_notes": null,
			"is_complex_parent": false,
			"reporter_only_notes": null,
			"temporarily_display_evac_zones": false
		},
		"date_created": "2025-03-03T14:20:17Z",
		"date_modified": "2025-03-03T17:36:33Z",
		"notification_type": "normal",
		"incident_id": null,
		"reporter_managed": true,
		"external_id": "{697D6C59-81FF-4DBB-9472-3904D90886A4}",
		"external_source": "nifc",
		"child_geo_events": [],
		"parent_geo_events": []
	},
	{
		"id": 42958,
		"is_active": true,
		"name": "Cloud Fire",
		"description": null,
		"lat": 34.389167,
		"lng": -97.408333,
		"address": null,
		"geo_event_type": "wildfire",
		"data": {
			"geo_event_type": "wildfire",
			"is_prescribed": false,
			"prescribed_date_start": null,
			"prescribed_date_start_local": null,
			"is_fps": false,
			"containment": 100,
			"acreage": 2.2,
			"links": null,
			"has_custom_evacuation_orders": false,
			"has_custom_evacuation_warnings": false,
			"has_custom_evacuation_advisories": false,
			"evacuation_orders": null,
			"evacuation_warnings": null,
			"evacuation_advisories": null,
			"evacuation_notes": null,
			"is_complex_parent": false,
			"reporter_only_notes": null,
			"temporarily_display_evac_zones": false
		},
		"date_created": "2025-03-03T14:25:18Z",
		"date_modified": "2025-03-03T17:26:33Z",
		"notification_type": "normal",
		"incident_id": null,
		"reporter_managed": true,
		"external_id": "{478F3989-1D08-4726-B820-0FEDCBA6EBA1}",
		"external_source": "nifc",
		"child_geo_events": [],
		"parent_geo_events": []
	},
	{
		"id": 42959,
		"is_active": false,
		"name": "Saline Creek Fire",
		"description": null,
		"lat": 36.314987,
		"lng": -94.905074,
		"address": "4 miles E of Kenwood, OK",
		"geo_event_type": "wildfire",
		"data": {
			"geo_event_type": "wildfire",
			"is_prescribed": false,
			"prescribed_date_start": null,
			"prescribed_date_start_local": null,
			"is_fps": null,
			"containment": 40,
			"acreage": 355,
			"links": null,
			"has_custom_evacuation_orders": false,
			"has_custom_evacuation_warnings": false,
			"has_custom_evacuation_advisories": false,
			"evacuation_orders": null,
			"evacuation_warnings": null,
			"evacuation_advisories": null,
			"evacuation_notes": null,
			"is_complex_parent": false,
			"reporter_only_notes": null,
			"temporarily_display_evac_zones": false
		},
		"date_created": "2025-03-03T14:30:27Z",
		"date_modified": "2025-03-03T16:25:20Z",
		"notification_type": "normal",
		"incident_id": null,
		"reporter_managed": false,
		"external_id": "{1056401C-0B7E-4C53-B6C6-A09C4DC466F9}",
		"external_source": "nifc",
		"child_geo_events": [],
		"parent_geo_events": []
	},
	{
		"id": 42960,
		"is_active": true,
		"name": "Bronco Fire",
		"description": null,
		"lat": 36.321389,
		"lng": -94.945278,
		"address": "3 miles NE of Kenwood, OK",
		"geo_event_type": "wildfire",
		"data": {
			"geo_event_type": "wildfire",
			"is_prescribed": false,
			"prescribed_date_start": null,
			"prescribed_date_start_local": null,
			"is_fps": null,
			"containment": 40,
			"acreage": 141.1,
			"links": null,
			"has_custom_evacuation_orders": false,
			"has_custom_evacuation_warnings": false,
			"has_custom_evacuation_advisories": false,
			"evacuation_orders": null,
			"evacuation_warnings": null,
			"evacuation_advisories": null,
			"evacuation_notes": null,
			"is_complex_parent": false,
			"reporter_only_notes": null,
			"temporarily_display_evac_zones": false
		},
		"date_created": "2025-03-03T14:45:27Z",
		"date_modified": "2025-03-03T16:15:20Z",
		"notification_type": "normal",
		"incident_id": null,
		"reporter_managed": false,
		"external_id": "{7C7076EC-27F5-4C3D-9CD1-9CBABFB75E28}",
		"external_source": "nifc",
		"child_geo_events": [],
		"parent_geo_events": []
	},
	{
		"id": 42962,
		"is_active": true,
		"name": "Steer Head Ranch Fire",
		"description": null,
		"lat": 44.394693,
		"lng": -106.768012,
		"address": null,
		"geo_event_type": "wildfire",
		"data": {
			"geo_event_type": "wildfire",
			"is_prescribed": false,
			"prescribed_date_start": null,
			"prescribed_date_start_local": null,
			"is_fps": null,
			"containment": null,
			"acreage": 4,
			"links": null,
			"has_custom_evacuation_orders": false,
			"has_custom_evacuation_warnings": false,
			"has_custom_evacuation_advisories": false,
			"evacuation_orders": null,
			"evacuation_warnings": null,
			"evacuation_advisories": null,
			"evacuation_notes": null,
			"is_complex_parent": false,
			"reporter_only_notes": null,
			"temporarily_display_evac_zones": false
		},
		"date_created": "2025-03-03T14:52:03Z",
		"date_modified": "2025-03-03T16:10:58Z",
		"notification_type": "normal",
		"incident_id": null,
		"reporter_managed": false,
		"external_id": "0b44f869-c3fd-4664-aec1-73f1405c9748",
		"external_source": "wildcad",
		"child_geo_events": [],
		"parent_geo_events": []
	},
	{
		"id": 42963,
		"is_active": true,
		"name": "Fire And Ice - Powder River Fire",
		"description": null,
		"lat": 45.45782,
		"lng": -105.3099,
		"address": null,
		"geo_event_type": "wildfire",
		"data": {
			"geo_event_type": "wildfire",
			"is_prescribed": false,
			"prescribed_date_start": null,
			"prescribed_date_start_local": null,
			"is_fps": false,
			"containment": 100,
			"acreage": 7.7,
			"links": null,
			"has_custom_evacuation_orders": false,
			"has_custom_evacuation_warnings": false,
			"has_custom_evacuation_advisories": false,
			"evacuation_orders": null,
			"evacuation_warnings": null,
			"evacuation_advisories": null,
			"evacuation_notes": null,
			"is_complex_parent": false,
			"reporter_only_notes": null,
			"temporarily_display_evac_zones": false
		},
		"date_created": "2025-03-03T14:55:27Z",
		"date_modified": "2025-03-03T16:59:33Z",
		"notification_type": "normal",
		"incident_id": null,
		"reporter_managed": true,
		"external_id": "{49FD8D16-A5E8-4F27-B1D1-D4562226632B}",
		"external_source": "nifc",
		"child_geo_events": [],
		"parent_geo_events": []
	},
	{
		"id": 42969,
		"is_active": true,
		"name": "Wood Pile - Mccone Fire",
		"description": null,
		"lat": 47.28037,
		"lng": -105.63342,
		"address": null,
		"geo_event_type": "wildfire",
		"data": {
			"geo_event_type": "wildfire",
			"is_prescribed": false,
			"prescribed_date_start": null,
			"prescribed_date_start_local": null,
			"is_fps": false,
			"containment": 100,
			"acreage": 14,
			"links": null,
			"has_custom_evacuation_orders": false,
			"has_custom_evacuation_warnings": false,
			"has_custom_evacuation_advisories": false,
			"evacuation_orders": null,
			"evacuation_warnings": null,
			"evacuation_advisories": null,
			"evacuation_notes": null,
			"is_complex_parent": false,
			"reporter_only_notes": null,
			"temporarily_display_evac_zones": false
		},
		"date_created": "2025-03-03T15:01:19Z",
		"date_modified": "2025-03-03T17:01:37Z",
		"notification_type": "normal",
		"incident_id": null,
		"reporter_managed": true,
		"external_id": "{1C6103D1-C0C1-4337-9CDE-DFE9423128CB}",
		"external_source": "nifc",
		"child_geo_events": [],
		"parent_geo_events": []
	},
	{
		"id": 42970,
		"is_active": true,
		"name": "Milton Fire",
		"description": null,
		"lat": 35.166667,
		"lng": -94.874444,
		"address": "4 miles E/NE of McCurtain, OK",
		"geo_event_type": "wildfire",
		"data": {
			"geo_event_type": "wildfire",
			"is_prescribed": false,
			"prescribed_date_start": null,
			"prescribed_date_start_local": null,
			"is_fps": false,
			"containment": 40,
			"acreage": 659,
			"links": null,
			"has_custom_evacuation_orders": false,
			"has_custom_evacuation_warnings": false,
			"has_custom_evacuation_advisories": false,
			"evacuation_orders": null,
			"evacuation_warnings": null,
			"evacuation_advisories": null,
			"evacuation_notes": null,
			"is_complex_parent": false,
			"reporter_only_notes": null,
			"temporarily_display_evac_zones": false
		},
		"date_created": "2025-03-03T15:05:19Z",
		"date_modified": "2025-03-03T17:17:32Z",
		"notification_type": "normal",
		"incident_id": null,
		"reporter_managed": true,
		"external_id": "{DEA7FB36-3ED0-47BA-9A56-499F7E9D4C43}",
		"external_source": "nifc",
		"child_geo_events": [],
		"parent_geo_events": []
	},
	{
		"id": 42974,
		"is_active": true,
		"name": "Pasture Fire",
		"description": null,
		"lat": 39.755,
		"lng": -96.648,
		"address": "900 Block of Quail Rd, Blue Rapids, KS 66411",
		"geo_event_type": "wildfire",
		"data": {
			"geo_event_type": "wildfire",
			"is_prescribed": false,
			"prescribed_date_start": null,
			"prescribed_date_start_local": null,
			"is_fps": false,
			"containment": 100,
			"acreage": 350,
			"links": null,
			"has_custom_evacuation_orders": false,
			"has_custom_evacuation_warnings": false,
			"has_custom_evacuation_advisories": false,
			"evacuation_orders": null,
			"evacuation_warnings": null,
			"evacuation_advisories": null,
			"evacuation_notes": null,
			"is_complex_parent": false,
			"reporter_only_notes": null,
			"temporarily_display_evac_zones": false
		},
		"date_created": "2025-03-03T16:05:20Z",
		"date_modified": "2025-03-03T16:24:15Z",
		"notification_type": "normal",
		"incident_id": null,
		"reporter_managed": true,
		"external_id": "{9FB6382C-3095-4C4F-9BF6-0EB75C04D977}",
		"external_source": "nifc",
		"child_geo_events": [],
		"parent_geo_events": []
	},
	{
		"id": 42988,
		"is_active": true,
		"name": "Lybrand Road Fire",
		"description": null,
		"lat": 34.526944,
		"lng": -93.738889,
		"address": null,
		"geo_event_type": "wildfire",
		"data": {
			"geo_event_type": "wildfire",
			"is_prescribed": false,
			"prescribed_date_start": null,
			"prescribed_date_start_local": null,
			"is_fps": null,
			"containment": null,
			"acreage": 2,
			"links": null,
			"has_custom_evacuation_orders": false,
			"has_custom_evacuation_warnings": false,
			"has_custom_evacuation_advisories": false,
			"evacuation_orders": null,
			"evacuation_warnings": null,
			"evacuation_advisories": null,
			"evacuation_notes": null,
			"is_complex_parent": false,
			"reporter_only_notes": null,
			"temporarily_display_evac_zones": false
		},
		"date_created": "2025-03-03T17:10:49Z",
		"date_modified": "2025-03-03T17:20:42Z",
		"notification_type": "normal",
		"incident_id": null,
		"reporter_managed": false,
		"external_id": "ca91c79c-bfcc-4ed8-ade1-77924599ef77",
		"external_source": "wildcad",
		"child_geo_events": [],
		"parent_geo_events": []
	},
	{
		"id": 42989,
		"is_active": true,
		"name": "630 Rd Fire",
		"description": null,
		"lat": 36.12,
		"lng": -94.403889,
		"address": "1.5 Mi Northeast of Lowrey, OK",
		"geo_event_type": "wildfire",
		"data": {
			"geo_event_type": "wildfire",
			"is_prescribed": false,
			"prescribed_date_start": null,
			"prescribed_date_start_local": null,
			"is_fps": null,
			"containment": 70,
			"acreage": 7.5,
			"links": null,
			"has_custom_evacuation_orders": false,
			"has_custom_evacuation_warnings": false,
			"has_custom_evacuation_advisories": false,
			"evacuation_orders": null,
			"evacuation_warnings": null,
			"evacuation_advisories": null,
			"evacuation_notes": null,
			"is_complex_parent": false,
			"reporter_only_notes": null,
			"temporarily_display_evac_zones": false
		},
		"date_created": "2025-03-03T17:11:21Z",
		"date_modified": "2025-03-03T17:11:21Z",
		"notification_type": "normal",
		"incident_id": null,
		"reporter_managed": false,
		"external_id": "{C3EE8A1D-45B0-417B-B076-A5F957A06052}",
		"external_source": "nifc",
		"child_geo_events": [],
		"parent_geo_events": []
	}
]